COPYING
COPYING.LESSER
MANIFEST.in
README.md
setup.cfg
setup.py
badlands/__init__.py
badlands/model.py
badlands.egg-info/PKG-INFO
badlands.egg-info/SOURCES.txt
badlands.egg-info/dependency_links.txt
badlands.egg-info/requires.txt
badlands.egg-info/top_level.txt
badlands/flow/__init__.py
badlands/flow/flowNetwork.py
badlands/flow/visualiseFlow.py
badlands/forcing/__init__.py
badlands/forcing/carbGrowth.py
badlands/forcing/forceSim.py
badlands/forcing/isoFlex.py
badlands/forcing/pelagicGrowth.py
badlands/forcing/xmlParser.py
badlands/hillslope/__init__.py
badlands/hillslope/diffLinear.py
badlands/simulation/__init__.py
badlands/simulation/buildFlux.py
badlands/simulation/buildMesh.py
badlands/simulation/checkPoints.py
badlands/simulation/waveSed.py
badlands/surface/FVmethod.py
badlands/surface/__init__.py
badlands/surface/elevationTIN.py
badlands/surface/partitionTIN.py
badlands/surface/raster2TIN.py
badlands/surface/visualiseTIN.py
badlands/underland/__init__.py
badlands/underland/carbMesh.py
badlands/underland/eroMesh.py
badlands/underland/strataMesh.py
badlands/underland/stratiWedge.py
utils/Makefile
utils/classfv.f90
utils/classfv.mod
utils/classfv.o
utils/classoro.f90
utils/classoro.mod
utils/classoro.o
utils/classpd.f90
utils/classpd.mod
utils/classpd.o
utils/flowalgo.f90
utils/flowalgo.pyf
utils/fourrier.mod
utils/fvframe.f90
utils/fvframe.pyf
utils/generate_pyf.sh
utils/m_mrgrnk.mod
utils/orderpack.mod
utils/ormodel.f90
utils/ormodel.pyf
utils/pdalgo.f90
utils/pdalgo.pyf
utils/sfd.c
utils/sfd.pyf
utils/waveseds.f90
utils/waveseds.pyf