Metadata-Version: 2.1
Name: badlands
Version: 2.2.3
Summary: Basin and Landscape Dynamics (Badlands) is a TIN-based landscape evolution model
Home-page: https://github.com/badlands-model
Author: Tristan Salles
Author-email: tristan.salles@sydney.edu.au
License: UNKNOWN
Platform: UNKNOWN
Classifier: Programming Language :: Python :: 3.5
Classifier: Programming Language :: Python :: 3.6
Classifier: Programming Language :: Python :: 3.7
Classifier: Programming Language :: Python :: 3.8
Requires-Python: >=3.5
License-File: COPYING
License-File: COPYING.LESSER
